zipy/__init__.py
zipy/cache.py
zipy/cmdline/__init__.py
zipy/cmdline/string.py
zipy/cmdline/web3.py
zipy/data.py
zipy/inspect.py
zipy/retry.py
zipy/time.py
zipy/web3.py
zipy-0.5.2.dist-info/METADATA
zipy-0.5.2.dist-info/WHEEL
zipy-0.5.2.dist-info/RECORD
